slint_compiler/__init__.py
slint_compiler-1.14.1b1.dist-info/METADATA
slint_compiler-1.14.1b1.dist-info/WHEEL
slint_compiler-1.14.1b1.dist-info/entry_points.txt
slint_compiler-1.14.1b1.dist-info/top_level.txt
slint_compiler-1.14.1b1.dist-info/RECORD
