Metadata-Version: 2.4
Name: slint-compiler
Version: 1.14.1b1
Summary: Python wrapper around the Slint compiler for Python
Author-email: Slint Team <info@slint.dev>
Project-URL: Homepage, https://slint.dev
Project-URL: Documentation, https://slint.dev/docs
Project-URL: Repository, https://github.com/slint-ui/slint
Project-URL: Changelog, https://github.com/slint-ui/slint/blob/master/CHANGELOG.md
Project-URL: Tracker, https://github.com/slint-ui/slint/issues
Requires-Python: >=3.10
Requires-Dist: cached-path>=1.7.3
